{
  "type": "bundle",
  "id": "bundle--20929cea-4719-4648-827f-7f078aaff78d",
  "objects": [
    {
      "type": "report",
      "spec_version": "2.1",
      "id": "report--68a0fd5f-09bb-4eac-8099-35f7090eacf7",
      "created": "2026-04-16T14:21:26.000Z",
      "modified": "2026-04-16T14:21:26.000Z",
      "name": "Defending Your Enterprise When AI Models Can Find Vulnerabilities Faster Than Ever",
      "description": "A significant shift in the economics of zero-day exploitation will enable mass exploitation campaigns, ransomware and extortion operations, and an increased volume of activity from actors who previously guarded these capabilities and used them sparingly.",
      "published": "2026-04-16T14:00:00.000Z",
      "report_types": [
        "threat-report"
      ],
      "object_refs": [
        "attack-pattern--b0ade7b9-7321-4c94-92dc-f6a98bbba1b4",
        "attack-pattern--84f45a79-6641-44fa-a8aa-5d47e75222ac",
        "attack-pattern--3777b913-b711-4d1a-86e4-5b16c5fdb5f1",
        "attack-pattern--ad78b96c-e828-4c73-8117-b99e9a0cc4ff"
      ],
      "external_references": [
        {
          "source_name": "Mandiant Blog",
          "url": "https://cloud.google.com/blog/topics/threat-intelligence/defending-enterprise-ai-vulnerabilities",
          "description": "Defending Your Enterprise When AI Models Can Find Vulnerabilities Faster Than Ever"
        }
      ],
      "labels": [
        "Government",
        "Media"
      ]
    },
    {
      "type": "attack-pattern",
      "spec_version": "2.1",
      "id": "attack-pattern--b0ade7b9-7321-4c94-92dc-f6a98bbba1b4",
      "created": "2026-04-16T14:21:26.000Z",
      "modified": "2026-04-16T14:21:26.000Z",
      "name": "Data Encrypted for Impact",
      "external_references": [
        {
          "source_name": "mitre-attack",
          "external_id": "T1486",
          "url": "https://attack.mitre.org/techniques/T1486/"
        }
      ],
      "kill_chain_phases": [
        {
          "kill_chain_name": "mitre-attack",
          "phase_name": "impact"
        }
      ]
    },
    {
      "type": "attack-pattern",
      "spec_version": "2.1",
      "id": "attack-pattern--84f45a79-6641-44fa-a8aa-5d47e75222ac",
      "created": "2026-04-16T14:21:26.000Z",
      "modified": "2026-04-16T14:21:26.000Z",
      "name": "Command and Scripting Interpreter",
      "external_references": [
        {
          "source_name": "mitre-attack",
          "external_id": "T1059",
          "url": "https://attack.mitre.org/techniques/T1059/"
        }
      ],
      "kill_chain_phases": [
        {
          "kill_chain_name": "mitre-attack",
          "phase_name": "execution"
        }
      ]
    },
    {
      "type": "attack-pattern",
      "spec_version": "2.1",
      "id": "attack-pattern--3777b913-b711-4d1a-86e4-5b16c5fdb5f1",
      "created": "2026-04-16T14:21:26.000Z",
      "modified": "2026-04-16T14:21:26.000Z",
      "name": "Exploit Public-Facing Application",
      "external_references": [
        {
          "source_name": "mitre-attack",
          "external_id": "T1190",
          "url": "https://attack.mitre.org/techniques/T1190/"
        }
      ],
      "kill_chain_phases": [
        {
          "kill_chain_name": "mitre-attack",
          "phase_name": "initial-access"
        }
      ]
    },
    {
      "type": "attack-pattern",
      "spec_version": "2.1",
      "id": "attack-pattern--ad78b96c-e828-4c73-8117-b99e9a0cc4ff",
      "created": "2026-04-16T14:21:26.000Z",
      "modified": "2026-04-16T14:21:26.000Z",
      "name": "Internal Spearphishing",
      "external_references": [
        {
          "source_name": "mitre-attack",
          "external_id": "T1534",
          "url": "https://attack.mitre.org/techniques/T1534/"
        }
      ],
      "kill_chain_phases": [
        {
          "kill_chain_name": "mitre-attack",
          "phase_name": "lateral-movement"
        }
      ]
    }
  ]
}