{
  "type": "bundle",
  "id": "bundle--31e306d1-00cb-4691-bdda-bfc41d109017",
  "objects": [
    {
      "type": "report",
      "spec_version": "2.1",
      "id": "report--6a6952d9-3c20-4814-b716-c45bf3e5d24e",
      "created": "2026-05-04T09:10:43.000Z",
      "modified": "2026-05-04T09:10:43.000Z",
      "name": "Instructure confirms data breach, ShinyHunters claims attack",
      "description": "Educational tech giant Instructure has confirmed that data was stolen in a cyberattack, with the ShinyHunters extortion gang claiming responsibility.",
      "published": "2026-05-03T22:16:27.000Z",
      "report_types": [
        "threat-report"
      ],
      "object_refs": [
        "report--6a6952d9-3c20-4814-b716-c45bf3e5d24e"
      ],
      "external_references": [
        {
          "source_name": "BleepingComputer",
          "url": "https://www.bleepingcomputer.com/news/security/instructure-confirms-data-breach-shinyhunters-claims-attack",
          "description": "Instructure confirms data breach, ShinyHunters claims attack"
        }
      ],
      "labels": [
        "Education"
      ]
    }
  ]
}